pyChakraCore/CHANGELOG.md
pyChakraCore/ChakraCommon.py
pyChakraCore/ChakraCore.py
pyChakraCore/README_CN.md
pyChakraCore/README_EN.md
pyChakraCore/__init__.py
pyChakraCore/test.py
pyChakraCore/linux/__init__.py
pyChakraCore/linux/libChakraCore.so
pyChakraCore/osx/__init__.py
pyChakraCore/osx/libChakraCore.dylib
pyChakraCore/windowsx64/ChakraCore.dll
pyChakraCore/windowsx64/__init__.py
pyChakraCore/windowsx86/ChakraCore.dll
pyChakraCore/windowsx86/__init__.py
pyChakraCore-0.2.0.dist-info/LICENSE
pyChakraCore-0.2.0.dist-info/METADATA
pyChakraCore-0.2.0.dist-info/WHEEL
pyChakraCore-0.2.0.dist-info/top_level.txt
pyChakraCore-0.2.0.dist-info/RECORD
